getadsilo/__init__.py
getadsilo/getadsilo.py
GetADSILO-0.1.dist-info/LICENSE
GetADSILO-0.1.dist-info/METADATA
GetADSILO-0.1.dist-info/WHEEL
GetADSILO-0.1.dist-info/entry_points.txt
GetADSILO-0.1.dist-info/top_level.txt
GetADSILO-0.1.dist-info/RECORD
