Metadata-Version: 2.1
Name: GetADSILO
Version: 0.1
Summary: GetADSILO is a Python script that queries Active Directory to list users and computers associated with authentication silos.
Home-page: https://github.com/WiseLife42/GetADSILO
Author: WiseLife
Author-email: 
Classifier: Programming Language :: Python :: 3
Classifier: License :: OSI Approved :: GNU General Public License v3 (GPLv3)
Classifier: Operating System :: OS Independent
Requires-Python: >=3.6
License-File: LICENSE
Requires-Dist: ldap3
Requires-Dist: python-dateutil
Requires-Dist: pycryptodome
Requires-Dist: rich
Requires-Dist: setuptools
